lcbtest/__init__.py
lcbtest-0.0.1.dist-info/METADATA
lcbtest-0.0.1.dist-info/WHEEL
lcbtest-0.0.1.dist-info/top_level.txt
lcbtest-0.0.1.dist-info/RECORD
